nbctl-0.1.3.dist-info/licenses/LICENSE
nbutils/__init__.py
nbutils/cli.py
nbutils/commands/__init__.py
nbutils/commands/clean.py
nbutils/commands/combine.py
nbutils/commands/diff.py
nbutils/commands/export.py
nbutils/commands/extract.py
nbutils/commands/format.py
nbutils/commands/git_setup.py
nbutils/commands/info.py
nbutils/commands/lint.py
nbutils/commands/ml_split.py
nbutils/commands/resolve.py
nbutils/commands/run.py
nbutils/commands/security.py
nbutils/core/__init__.py
nbutils/core/cleaner.py
nbutils/core/differ.py
nbutils/core/merger.py
nbutils/core/notebook.py
nbctl-0.1.3.dist-info/METADATA
nbctl-0.1.3.dist-info/WHEEL
nbctl-0.1.3.dist-info/entry_points.txt
nbctl-0.1.3.dist-info/top_level.txt
nbctl-0.1.3.dist-info/RECORD
