Metadata-Version: 2.4
Name: nbctl
Version: 0.1.3
Summary: A comprehensive, modern CLI toolkit that solves all major Jupyter notebook pain points in one unified interface.
Author-email: Venkatachalam Subramanian Periya Subbu <venkatachalam.sps@gmail.com>
License: MIT
Project-URL: Homepage, https://github.com/VenkatachalamSubramanianPeriyaSubbu/nbctl
Project-URL: Documentation, https://venkatachalamsubramanianperiyasubbu.github.io/nbctl/
Project-URL: Repository, https://github.com/VenkatachalamSubramanianPeriyaSubbu/nbctl
Project-URL: Issues, https://github.com/VenkatachalamSubramanianPeriyaSubbu/nbctl/issues
Classifier: Development Status :: 4 - Beta
Classifier: Intended Audience :: Developers
Classifier: Intended Audience :: Science/Research
Classifier: Intended Audience :: Education
Classifier: License :: OSI Approved :: MIT License
Classifier: Programming Language :: Python :: 3
Classifier: Programming Language :: Python :: 3.8
Classifier: Programming Language :: Python :: 3.9
Classifier: Programming Language :: Python :: 3.10
Classifier: Programming Language :: Python :: 3.11
Classifier: Programming Language :: Python :: 3.12
Classifier: Topic :: Software Development :: Quality Assurance
Classifier: Topic :: Software Development :: Version Control
Classifier: Topic :: Scientific/Engineering
Classifier: Operating System :: OS Independent
Classifier: Environment :: Console
Requires-Python: >=3.8
License-File: LICENSE
Requires-Dist: nbformat>=5.0.0
Requires-Dist: click>=8.0.0
Requires-Dist: rich>=13.0.0
Requires-Dist: nbconvert>=7.0.0
Requires-Dist: nbclient>=0.7.0
Requires-Dist: nbdime>=3.0.0
Provides-Extra: dev
Requires-Dist: pytest>=7.0.0; extra == "dev"
Requires-Dist: pytest-cov>=4.0.0; extra == "dev"
Requires-Dist: black>=23.0.0; extra == "dev"
Requires-Dist: mypy>=1.0.0; extra == "dev"
Dynamic: license-file
